langchain_stardog/__init__.py
langchain_stardog/voicebox/__init__.py
langchain_stardog/voicebox/client.py
langchain_stardog/voicebox/constants.py
langchain_stardog/voicebox/exceptions.py
langchain_stardog/voicebox/runnables.py
langchain_stardog/voicebox/tools.py
langchain_stardog-0.1.1.dist-info/METADATA
langchain_stardog-0.1.1.dist-info/WHEEL
langchain_stardog-0.1.1.dist-info/licenses/LICENSE
langchain_stardog-0.1.1.dist-info/RECORD
