Metadata-Version: 2.4
Name: langchain-stardog
Version: 0.1.1
Summary: LangChain integrations for Stardog
Author-email: Stardog Union <support@stardog.com>
License: Apache-2.0
License-File: LICENSE
Keywords: knowledge-graph,langchain,sparql,stardog,voicebox
Classifier: Development Status :: 4 - Beta
Classifier: Intended Audience :: Developers
Classifier: License :: OSI Approved :: Apache Software License
Classifier: Programming Language :: Python :: 3
Classifier: Programming Language :: Python :: 3.10
Classifier: Programming Language :: Python :: 3.11
Classifier: Programming Language :: Python :: 3.12
Classifier: Topic :: Scientific/Engineering :: Artificial Intelligence
Classifier: Topic :: Software Development :: Libraries :: Python Modules
Requires-Python: >=3.10
Requires-Dist: httpx>=0.28.0
Requires-Dist: langchain-core==1.0.0
Requires-Dist: pydantic>=2.11.0
Requires-Dist: pystardog>=0.19.0
Provides-Extra: dev
Requires-Dist: black==25.1.0; extra == 'dev'
Requires-Dist: flake8==7.3.0; extra == 'dev'
Requires-Dist: isort==6.0.1; extra == 'dev'
Requires-Dist: langchain-tests==0.3.21; extra == 'dev'
Requires-Dist: langchain==1.0.0; extra == 'dev'
Requires-Dist: mypy==1.17.1; extra == 'dev'
Requires-Dist: pytest-asyncio==1.1.0; extra == 'dev'
Requires-Dist: pytest-cov>=6.2.1; extra == 'dev'
Requires-Dist: pytest==8.4.1; extra == 'dev'
